CHANGELOG
COPYRIGHT
LICENSE
MANIFEST.in
README
setup.py
escpos_xml/__init__.py
escpos_xml/__main__.py
escpos_xml/escpos.rnc
escpos_xml/escpos.rng
escpos_xml/parser.py
escpos_xml/tests/__init__.py
escpos_xml/tests/image.xml
escpos_xml/tests/test_parser.py
python_escpos_xml.egg-info/PKG-INFO
python_escpos_xml.egg-info/SOURCES.txt
python_escpos_xml.egg-info/dependency_links.txt
python_escpos_xml.egg-info/requires.txt
python_escpos_xml.egg-info/top_level.txt