Metadata-Version: 1.1
Name: python-escpos-xml
Version: 0.1.0
Summary: Print XML defined receipt on ESC/POS Printer
Home-page: http://hg.b2ck.com/python-escpos-xml/
Author: B2CK
Author-email: info@b2ck.com
License: LGPL-3
Platform: UNKNOWN
Classifier: Development Status :: 5 - Production/Stable
Classifier: Intended Audience :: Developers
Classifier: License :: OSI Approved :: GNU General Public License v3 (GPLv3)
Classifier: Operating System :: OS Independent
Classifier: Programming Language :: Python :: 2.7
Classifier: Topic :: Office/Business :: Financial
Classifier: Topic :: Software Development :: Libraries :: Python Modules
